arkon_schema/__init__.py
arkon_schema-0.0.1.dev0.dist-info/LICENSE
arkon_schema-0.0.1.dev0.dist-info/WHEEL
arkon_schema-0.0.1.dev0.dist-info/METADATA
arkon_schema-0.0.1.dev0.dist-info/RECORD
