Metadata-Version: 2.1
Name: arkon-schema
Version: 0.0.1.dev0
Summary: Arkon protobuf library
Author: Nick Groszewski
Author-email: groszewn@gmail.com
Requires-Python: >=3.9,<4.0
Classifier: Programming Language :: Python :: 3
Classifier: Programming Language :: Python :: 3.9
